pystave/__init__.py
pystave/__main__.py
pystave/analysis.py
pystave/images/clef_bass.png
pystave/images/clef_treble.png
pystave/images/doubleflat.png
pystave/images/doublesharp.png
pystave/images/flat.png
pystave/images/icon.png
pystave/images/ledger_line.png
pystave/images/natural.png
pystave/images/note_filled.png
pystave/images/note_open.png
pystave/images/sharp.png
pystave/images/stave.png
pystave-1.3.1.dist-info/licenses/COPYING
pystave-1.3.1.dist-info/licenses/LICENSE
pystave-1.3.1.dist-info/METADATA
pystave-1.3.1.dist-info/WHEEL
pystave-1.3.1.dist-info/entry_points.txt
pystave-1.3.1.dist-info/top_level.txt
pystave-1.3.1.dist-info/RECORD
