Metadata-Version: 2.4
Name: pystave
Version: 1.3.1
Summary: musical stave trainer
Home-page: https://bitbucket.org/jezhill/pystave
Author: Jeremy Hill
Author-email: jezhill@gmail.com
License: GPLv3+
Classifier: License :: OSI Approved :: GNU General Public License v3 or later (GPLv3+)
Classifier: Programming Language :: Python :: 2.7
Classifier: Programming Language :: Python :: 3
License-File: LICENSE
License-File: COPYING
Requires-Dist: pygame
Dynamic: author
Dynamic: author-email
Dynamic: classifier
Dynamic: description
Dynamic: description-content-type
Dynamic: home-page
Dynamic: license
Dynamic: license-file
Dynamic: requires-dist
Dynamic: summary
